it_helpdesk/__init__.py
it_helpdesk/ansible/help_templates/manage_users_help.txt
it_helpdesk/ansible/help_templates/storage_help.txt
it_helpdesk/ansible/inventory
it_helpdesk/ansible/phrasebooks/.keywords.txt
it_helpdesk/ansible/phrasebooks/account_phrases.txt
it_helpdesk/ansible/phrasebooks/help_phrases.txt
it_helpdesk/ansible/phrasebooks/manage_account_phrases.txt
it_helpdesk/ansible/phrasebooks/manage_users_phrases.txt
it_helpdesk/ansible/phrasebooks/storage_phrases.txt
it_helpdesk/ansible/playbooks/help.yaml
it_helpdesk/ansible/playbooks/manage_users.yaml
it_helpdesk/ansible/playbooks/storage.yaml
it_helpdesk/ansible/sample_email.txt
it_helpdesk/ansible/vars/ansible.cfg
it_helpdesk/get_request_email.py
it_helpdesk/mail_script.py
it_helpdesk/request_parser.py
it_helpdesk/setup.py
it_helpdesk-0.1.1.dist-info/LICENSE
it_helpdesk-0.1.1.dist-info/METADATA
it_helpdesk-0.1.1.dist-info/WHEEL
it_helpdesk-0.1.1.dist-info/entry_points.txt
it_helpdesk-0.1.1.dist-info/RECORD
