Metadata-Version: 2.1
Name: it-helpdesk
Version: 0.1.1
Summary: This is an open-source plaintext email based IT helpdesk that requires no manual interaction.
License: MIT Licensed
Author: Arnav Sajith
Author-email: arnavsajith04@gmail.com
Requires-Python: >=3.11,<4.0
Classifier: License :: Other/Proprietary License
Classifier: Programming Language :: Python :: 3
Classifier: Programming Language :: Python :: 3.11
Classifier: Programming Language :: Python :: 3.12
Requires-Dist: ansible (>=8.5.0,<9.0.0)
Requires-Dist: ansible-runner (>=2.3.4,<3.0.0)
Requires-Dist: inquirerpy (>=0.3.4,<0.4.0)
Requires-Dist: wheel (>=0.42.0,<0.43.0)
